aamaze/__init__.py
aamaze/base_maze.py
aamaze/generation/__init__.py
aamaze/generation/eller.py
aamaze/generation/growing_tree.py
aamaze/generation/kruskals.py
aamaze/generation/prims.py
aamaze/generation/recursive_backtracker.py
aamaze/generation/recursive_divisior.py
aamaze/generation/wilsons.py
aamaze/graphics/__init__.py
aamaze/graphics/app.py
aamaze/graphics/defaults.py
aamaze/graphics/draw_maze.py
aamaze/solving/__init__.py
aamaze/solving/a_star.py
aamaze/solving/dijkstra.py
aamaze/solving/flood_fill.py
aamaze-0.3.3.dist-info/LICENSE
aamaze-0.3.3.dist-info/METADATA
aamaze-0.3.3.dist-info/WHEEL
aamaze-0.3.3.dist-info/RECORD
