Metadata-Version: 2.1
Name: aamaze
Version: 0.3.3
Summary: A python package for generating, solving and displaying mazes.
Home-page: https://github.com/aaFurze/aamaze
License: MIT
Keywords: maze,algorithm,maze generation,maze solution,display,draw
Author: aaFurze
Author-email: aafurze@gmail.com
Requires-Python: >=3.9,<4.0
Classifier: License :: OSI Approved :: MIT License
Classifier: Programming Language :: Python :: 3
Classifier: Programming Language :: Python :: 3.9
Classifier: Programming Language :: Python :: 3.10
Classifier: Programming Language :: Python :: 3.11
Requires-Dist: pygame (>=2.0.0,<3.0.0)
Project-URL: Repository, https://github.com/aaFurze/aamaze
